{
  "experiment": "Confidence Threshold + Fallback (Experiment 4)",
  "timestamp": "2026-04-09T16:36:42.932078",
  "dataset": "adversarial_v2_hard (200 samples)",
  "model": "microsoft/phi-2",
  "device": "cuda",
  "threshold_configs": {
    "always_accept": {
      "min_confidence": 0.0,
      "min_margin": 0.0
    },
    "threshold_0.5": {
      "min_confidence": 0.5,
      "min_margin": 0.03
    },
    "threshold_0.6": {
      "min_confidence": 0.6,
      "min_margin": 0.05
    },
    "threshold_0.7": {
      "min_confidence": 0.7,
      "min_margin": 0.08
    }
  },
  "primary_method": "threshold_0.6",
  "always_accept": {
    "overall": {
      "edit_acc": 0.74,
      "rephrase_acc": 0.775,
      "locality_acc": 1,
      "portability_acc": 0.135,
      "retrieval_score": 0.9556,
      "eval_time_seconds": 941.3,
      "rejection_count": 0,
      "rejection_rate": 0.0,
      "accepted_count": 200,
      "rejected_acc": 0,
      "accepted_acc": 0.74,
      "avg_score": 0.9556,
      "avg_margin": 0.3177
    },
    "per_category": {
      "ambiguity": {
        "edit_acc": 0.78,
        "rephrase_acc": 0.64,
        "locality_acc": 1,
        "portability_acc": 0.18,
        "retrieval_score": 0.9509,
        "count": 50
      },
      "reasoning_failure": {
        "edit_acc": 0.65,
        "rephrase_acc": 0.65,
        "locality_acc": 1,
        "portability_acc": 0.1,
        "retrieval_score": 0.9635,
        "count": 40
      },
      "retrieval_error": {
        "edit_acc": 0.9,
        "rephrase_acc": 0.925,
        "locality_acc": 1,
        "portability_acc": 0.15,
        "retrieval_score": 0.9781,
        "count": 40
      },
      "hard_distinction": {
        "edit_acc": 0.7667,
        "rephrase_acc": 0.9,
        "locality_acc": 1,
        "portability_acc": 0.1,
        "retrieval_score": 0.9385,
        "count": 30
      },
      "conflicting_signals": {
        "edit_acc": 0.6,
        "rephrase_acc": 0.825,
        "locality_acc": 1,
        "portability_acc": 0.125,
        "retrieval_score": 0.9441,
        "count": 40
      }
    }
  },
  "threshold_0.5": {
    "overall": {
      "edit_acc": 0.74,
      "rephrase_acc": 0.775,
      "locality_acc": 1,
      "portability_acc": 0.135,
      "retrieval_score": 0.9556,
      "eval_time_seconds": 935.22,
      "rejection_count": 1,
      "rejection_rate": 0.005,
      "accepted_count": 199,
      "rejected_acc": 1.0,
      "accepted_acc": 0.7387,
      "avg_score": 0.9556,
      "avg_margin": 0.3177,
      "avg_rejected_score": 0.9906,
      "avg_rejected_margin": 0.0209
    },
    "per_category": {
      "ambiguity": {
        "edit_acc": 0.78,
        "rephrase_acc": 0.64,
        "locality_acc": 1,
        "portability_acc": 0.18,
        "retrieval_score": 0.9509,
        "count": 50
      },
      "reasoning_failure": {
        "edit_acc": 0.65,
        "rephrase_acc": 0.65,
        "locality_acc": 1,
        "portability_acc": 0.1,
        "retrieval_score": 0.9635,
        "count": 40
      },
      "retrieval_error": {
        "edit_acc": 0.9,
        "rephrase_acc": 0.925,
        "locality_acc": 1,
        "portability_acc": 0.15,
        "retrieval_score": 0.9781,
        "count": 40
      },
      "hard_distinction": {
        "edit_acc": 0.7667,
        "rephrase_acc": 0.9,
        "locality_acc": 1,
        "portability_acc": 0.1,
        "retrieval_score": 0.9385,
        "count": 30
      },
      "conflicting_signals": {
        "edit_acc": 0.6,
        "rephrase_acc": 0.825,
        "locality_acc": 1,
        "portability_acc": 0.125,
        "retrieval_score": 0.9441,
        "count": 40
      }
    }
  },
  "threshold_0.6": {
    "overall": {
      "edit_acc": 0.73,
      "rephrase_acc": 0.765,
      "locality_acc": 1,
      "portability_acc": 0.135,
      "retrieval_score": 0.9556,
      "eval_time_seconds": 934.83,
      "rejection_count": 4,
      "rejection_rate": 0.02,
      "accepted_count": 196,
      "rejected_acc": 0.5,
      "accepted_acc": 0.7347,
      "avg_score": 0.9556,
      "avg_margin": 0.3177,
      "avg_rejected_score": 0.9946,
      "avg_rejected_margin": 0.031
    },
    "per_category": {
      "ambiguity": {
        "edit_acc": 0.78,
        "rephrase_acc": 0.64,
        "locality_acc": 1,
        "portability_acc": 0.18,
        "retrieval_score": 0.9509,
        "count": 50
      },
      "reasoning_failure": {
        "edit_acc": 0.65,
        "rephrase_acc": 0.65,
        "locality_acc": 1,
        "portability_acc": 0.1,
        "retrieval_score": 0.9635,
        "count": 40
      },
      "retrieval_error": {
        "edit_acc": 0.85,
        "rephrase_acc": 0.875,
        "locality_acc": 1,
        "portability_acc": 0.15,
        "retrieval_score": 0.9781,
        "count": 40
      },
      "hard_distinction": {
        "edit_acc": 0.7667,
        "rephrase_acc": 0.9,
        "locality_acc": 1,
        "portability_acc": 0.1,
        "retrieval_score": 0.9385,
        "count": 30
      },
      "conflicting_signals": {
        "edit_acc": 0.6,
        "rephrase_acc": 0.825,
        "locality_acc": 1,
        "portability_acc": 0.125,
        "retrieval_score": 0.9441,
        "count": 40
      }
    }
  },
  "threshold_0.7": {
    "overall": {
      "edit_acc": 0.71,
      "rephrase_acc": 0.75,
      "locality_acc": 1,
      "portability_acc": 0.145,
      "retrieval_score": 0.9556,
      "eval_time_seconds": 949.92,
      "rejection_count": 13,
      "rejection_rate": 0.065,
      "accepted_count": 187,
      "rejected_acc": 0.3846,
      "accepted_acc": 0.7326,
      "avg_score": 0.9556,
      "avg_margin": 0.3177,
      "avg_rejected_score": 0.9894,
      "avg_rejected_margin": 0.0551
    },
    "per_category": {
      "ambiguity": {
        "edit_acc": 0.76,
        "rephrase_acc": 0.62,
        "locality_acc": 1,
        "portability_acc": 0.18,
        "retrieval_score": 0.9509,
        "count": 50
      },
      "reasoning_failure": {
        "edit_acc": 0.65,
        "rephrase_acc": 0.65,
        "locality_acc": 1,
        "portability_acc": 0.1,
        "retrieval_score": 0.9635,
        "count": 40
      },
      "retrieval_error": {
        "edit_acc": 0.775,
        "rephrase_acc": 0.825,
        "locality_acc": 1,
        "portability_acc": 0.2,
        "retrieval_score": 0.9781,
        "count": 40
      },
      "hard_distinction": {
        "edit_acc": 0.7667,
        "rephrase_acc": 0.9,
        "locality_acc": 1,
        "portability_acc": 0.1,
        "retrieval_score": 0.9385,
        "count": 30
      },
      "conflicting_signals": {
        "edit_acc": 0.6,
        "rephrase_acc": 0.825,
        "locality_acc": 1,
        "portability_acc": 0.125,
        "retrieval_score": 0.9441,
        "count": 40
      }
    }
  },
  "deltas": {
    "edit_acc": -0.01,
    "rephrase_acc": -0.01,
    "locality_acc": 0,
    "portability_acc": 0.0,
    "retrieval_score": 0.0
  },
  "all_deltas": {
    "always_accept": {
      "edit_acc": 0.0,
      "rephrase_acc": 0.0,
      "locality_acc": 0,
      "portability_acc": 0.0,
      "retrieval_score": 0.0
    },
    "threshold_0.5": {
      "edit_acc": 0.0,
      "rephrase_acc": 0.0,
      "locality_acc": 0,
      "portability_acc": 0.0,
      "retrieval_score": 0.0
    },
    "threshold_0.6": {
      "edit_acc": -0.01,
      "rephrase_acc": -0.01,
      "locality_acc": 0,
      "portability_acc": 0.0,
      "retrieval_score": 0.0
    },
    "threshold_0.7": {
      "edit_acc": -0.03,
      "rephrase_acc": -0.025,
      "locality_acc": 0,
      "portability_acc": 0.01,
      "retrieval_score": 0.0
    }
  },
  "category_edit_deltas": {
    "ambiguity": {
      "always_accept": 0.78,
      "threshold_0.6": 0.78,
      "delta": 0.0,
      "threshold_0.5": 0.78,
      "threshold_0.7": 0.76
    },
    "conflicting_signals": {
      "always_accept": 0.6,
      "threshold_0.6": 0.6,
      "delta": 0.0,
      "threshold_0.5": 0.6,
      "threshold_0.7": 0.6
    },
    "hard_distinction": {
      "always_accept": 0.7667,
      "threshold_0.6": 0.7667,
      "delta": 0.0,
      "threshold_0.5": 0.7667,
      "threshold_0.7": 0.7667
    },
    "reasoning_failure": {
      "always_accept": 0.65,
      "threshold_0.6": 0.65,
      "delta": 0.0,
      "threshold_0.5": 0.65,
      "threshold_0.7": 0.65
    },
    "retrieval_error": {
      "always_accept": 0.9,
      "threshold_0.6": 0.85,
      "delta": -0.05,
      "threshold_0.5": 0.9,
      "threshold_0.7": 0.775
    }
  }
}